MANIFEST.in
README.txt
setup.py
c2/__init__.py
c2.patch.jashortname.egg-info/PKG-INFO
c2.patch.jashortname.egg-info/SOURCES.txt
c2.patch.jashortname.egg-info/dependency_links.txt
c2.patch.jashortname.egg-info/entry_points.txt
c2.patch.jashortname.egg-info/namespace_packages.txt
c2.patch.jashortname.egg-info/not-zip-safe
c2.patch.jashortname.egg-info/requires.txt
c2.patch.jashortname.egg-info/top_level.txt
c2/patch/__init__.py
c2/patch/jashortname/__init__.py
c2/patch/jashortname/configure.zcml
c2/patch/jashortname/normalizer.py
c2/patch/jashortname/overrides.zcml
c2/patch/jashortname/tests.py
c2/patch/jashortname/version.txt
docs/HISTORY.txt
docs/INSTALL.txt
docs/LICENSE.GPL
docs/LICENSE.txt