Metadata-Version: 1.1
Name: c2.patch.jashortname
Version: 1.0a1
Summary: This product is patching for Japanese shortname for Plone files
Home-page: https://bitbucket.org/cmscom/c2.patch.jashortname
Author: Manabu TERADA
Author-email: terada@cmscom.jp
License: GPL
Keywords: plone patch shortname japanese
Platform: UNKNOWN
Classifier: Framework :: Plone
Classifier: Programming Language :: Python
